checkalive.py
checkalive-0.1.9.dist-info/LICENSE
checkalive-0.1.9.dist-info/METADATA
checkalive-0.1.9.dist-info/WHEEL
checkalive-0.1.9.dist-info/entry_points.txt
checkalive-0.1.9.dist-info/top_level.txt
checkalive-0.1.9.dist-info/RECORD
