Metadata-Version: 2.1
Name: checkalive
Version: 0.1.9
Summary: 检查系统状态，如：指定的IP地址是否存在，指定的端口是否被监听，指定的进程是否存活。
Home-page: https://github.com/appstore-zencore/checkalive
Author: zencore
Author-email: dobetter@zencore.cn
License: MIT
Keywords: openpyxl,xlsx split,excel split
Platform: UNKNOWN
Classifier: Development Status :: 5 - Production/Stable
Classifier: Intended Audience :: Developers
Classifier: Topic :: Software Development :: Libraries :: Python Modules
Classifier: License :: OSI Approved :: MIT License
Classifier: Programming Language :: Python :: 3
Classifier: Programming Language :: Python :: 3 :: Only
Requires-Dist: six (>=1.12.0)
Requires-Dist: click
Requires-Dist: psutil
